MANIFEST.in
README.rst
setup.py
clashroyale/__init__.py
clashroyale/constants.json
clashroyale/errors.py
clashroyale.egg-info/PKG-INFO
clashroyale.egg-info/SOURCES.txt
clashroyale.egg-info/dependency_links.txt
clashroyale.egg-info/requires.txt
clashroyale.egg-info/top_level.txt
clashroyale/official_api/__init__.py
clashroyale/official_api/client.py
clashroyale/official_api/models.py
clashroyale/official_api/utils.py
clashroyale/royaleapi/__init__.py
clashroyale/royaleapi/client.py
clashroyale/royaleapi/models.py
clashroyale/royaleapi/utils.py