Metadata-Version: 2.1
Name: clashroyale
Version: 4.0.1
Summary: An (a)sync wrapper for royaleapi.com
Home-page: UNKNOWN
License: MIT
Project-URL: Source Code, https://github.com/cgrok/clashroyale
Project-URL: Issue Tracker, https://github.com/cgrok/clashroyale/issues
Project-URL: Documentation, https://clashroyale.readthedocs.io/
Keywords: clashroyale,wrapper,cr,royaleapi
Platform: UNKNOWN
Classifier: Development Status :: 5 - Production/Stable
Classifier: Intended Audience :: Developers
Classifier: Topic :: Games/Entertainment :: Real Time Strategy
Classifier: License :: OSI Approved :: MIT License
Classifier: Programming Language :: Python :: 3.5
Classifier: Programming Language :: Python :: 3.6
Classifier: Programming Language :: Python :: 3.7
Classifier: Programming Language :: Python :: Implementation :: CPython
Classifier: Natural Language :: English
Requires-Python: >=3.5
